pdfy/__init__.py
pdfy/models.py
pdfy/views.py
pdfy/tests/__init__.py
pdfy/tests/test_settings.py
pdfy/tests/test_views.py
django_pdfy-0.2.3.dist-info/AUTHORS
django_pdfy-0.2.3.dist-info/LICENSE
django_pdfy-0.2.3.dist-info/METADATA
django_pdfy-0.2.3.dist-info/WHEEL
django_pdfy-0.2.3.dist-info/top_level.txt
django_pdfy-0.2.3.dist-info/RECORD
