Metadata-Version: 2.1
Name: django-pdfy
Version: 0.2.3
Summary: <Include a description of your project>
Home-page: https://github.com/rochapps/django-pdfy
Author: Victor Rocha
Author-email: victor@rochapps.com
License: BDS
Platform: UNKNOWN
Classifier: Topic :: Internet :: WWW/HTTP :: Dynamic Content
Classifier: Intended Audience :: Developers
Classifier: Programming Language :: Python
Classifier: Programming Language :: Python :: 2.6
Classifier: Programming Language :: Python :: 2.7
Classifier: Framework :: Django
Classifier: Development Status :: 4 - Beta
Classifier: Operating System :: OS Independent
Requires-Dist: django (>1.11)
Requires-Dist: xhtml2pdf (==0.2.3)
